py_lambda/__init__.py
py_lambda/all_Functions.py
py_lambda/funct_defines.py
py_lambda/inp_validatn.py
py_lambda/lambda_defines.py
py_lambda/lambda_function.py
py_lambda/lambda_mapping.py
py_lambda/request.py
py_lambda/response.py
py_lambda/setup.py
py_lambda/test_LambdaHandler.py
py_lambda-1.1.5.dist-info/LICENCE.txt
py_lambda-1.1.5.dist-info/METADATA
py_lambda-1.1.5.dist-info/WHEEL
py_lambda-1.1.5.dist-info/top_level.txt
py_lambda-1.1.5.dist-info/RECORD
