Metadata-Version: 2.1
Name: py-lambda
Version: 1.1.5
Summary: Lambda framework for AWS
Home-page: https://github.com/ajayau404/AWS-Py-Lambda
Author: Ajay A U
Author-email: ajayau404@gmail.com
License: Apache License 2.0
Platform: UNKNOWN
Classifier: Development Status :: 5 - Production/Stable
Classifier: Intended Audience :: Developers
Classifier: License :: OSI Approved :: Apache Software License
Classifier: Natural Language :: English
Classifier: Programming Language :: Python :: 2
Classifier: Programming Language :: Python :: 2.7
Classifier: Programming Language :: Python :: 3.6
Requires-Dist: wheel
Requires-Dist: setuptools
